src/rtl/sv32.vh
/*
 *  kianv harris multicycle RISC-V rv32ima
 *
 *  copyright (c) 2023 hirosh dabui <hirosh@dabui.de>
 *
 *  permission to use, copy, modify, and/or distribute this software for any
 *  purpose with or without fee is hereby granted, provided that the above
 *  copyright notice and this permission notice appear in all copies.
 *
 *  the software is provided "as is" and the author disclaims all warranties
 *  with regard to this software including all implied warranties of
 *  merchantability and fitness. in no event shall the author be liable for
 *  any special, direct, indirect, or consequential damages or any damages
 *  whatsoever resulting from loss of use, data or profits, whether in an
 *  action of contract, negligence or other tortious action, arising out of
 *  or in connection with the use or performance of this software.
 *
 */
`ifndef SV32_VH
`define SV32_VH

`define SV32_LEVELS 2
`define SV32_PTE_SIZE 4  // size in bytes
`define SV32_PTE_SHIFT 2
`define SV32_PTE_V_SHIFT 0  // Valid bit position
`define SV32_PTE_R_SHIFT 1  // Read bit position
`define SV32_PTE_W_SHIFT 2  // Write bit position
`define SV32_PTE_X_SHIFT 3  // Execute bit position
`define SV32_PTE_U_SHIFT 4  // User bit position
`define SV32_PTE_G_SHIFT 5  // Global bit position
`define SV32_PTE_A_SHIFT 6  // Accessed bit position
`define SV32_PTE_D_SHIFT 7  // Dirty bit position
`define SV32_PTE_RSW_SHIFT 8  // Reserved for Software use
`define SV32_PTE_PPN_SHIFT 10  // Physical Page Number bit position
`define SV32_PTE_ALIGNED_PPN_SHIFT (`SV32_PTE_PPN_SHIFT + 2)

`define SV32_PTE_PPN_BITS 22  // Number of bits for Physical Page Number
`define SV32_PAGE_SIZE 4096  // Page size in bytes (4 KiB for Sv32)
`define SV32_PAGE_OFFSET_BITS 12  // Number of bits for page offset (log2 of page size)

`define SV32_OFFSET_BITS 12
`define SV32_VPN0_BITS 10
`define SV32_VPN1_BITS 10

`define SV32_SATP_MODE_MASK 31

`define SV32_OFFSET_MASK ((32'h1 << `SV32_OFFSET_BITS) - 1)
`define SV32_VPN0_MASK (((32'h1 << `SV32_VPN0_BITS) - 1) << `SV32_OFFSET_BITS)
`define SV32_VPN1_MASK (((32'h1 << `SV32_VPN1_BITS) - 1) << (`SV32_OFFSET_BITS + `SV32_VPN0_BITS))

`define SV32_VPN0_SHIFT 10
`define SV32_VPN1_SHIFT (`SV32_OFFSET_BITS + `SV32_VPN0_BITS)

`define PTE_V_MASK (32'h1 << 0)
`define PTE_R_MASK (32'h1 << 1)
`define PTE_W_MASK (32'h1 << 2)
`define PTE_X_MASK (32'h1 << 3)
`define PTE_U_MASK (32'h1 << 4)
`define PTE_G_MASK (32'h1 << 5)
`define PTE_A_MASK (32'h1 << 6)
`define PTE_D_MASK (32'h1 << 7)
`define PTE_RSW_MASK (32'h3 << 8)  // 2 bits for RSW
`define PTE_PPN_MASK 32'hFFFFF000  // 22 bits for PPN
`define PTE_FLAGS 32'h3FF

`define SET_PTE_V(pte, val) ((val) << 0)
`define SET_PTE_R(pte, val) ((val) << 1)
`define SET_PTE_W(pte, val) ((val) << 2)
`define SET_PTE_X(pte, val) ((val) << 3)
`define SET_PTE_U(pte, val) ((val) << 4)
`define SET_PTE_G(pte, val) ((val) << 5)
`define SET_PTE_A(pte, val) ((val) << 6)
`define SET_PTE_D(pte, val) ((val) << 7)
`define SET_PTE_RSW(pte, val) ((val) << 8)
`define SET_PTE_PPN(pte, val) ((val) << 10)

`define GET_PTE_V(pte) (((pte) & `PTE_V_MASK) >> 0)
`define GET_PTE_R(pte) (((pte) & `PTE_R_MASK) >> 1)
`define GET_PTE_W(pte) (((pte) & `PTE_W_MASK) >> 2)
`define GET_PTE_X(pte) (((pte) & `PTE_X_MASK) >> 3)
`define GET_PTE_U(pte) (((pte) & `PTE_U_MASK) >> 4)
`define GET_PTE_G(pte) (((pte) & `PTE_G_MASK) >> 5)
`define GET_PTE_A(pte) (((pte) & `PTE_A_MASK) >> 6)
`define GET_PTE_D(pte) (((pte) & `PTE_D_MASK) >> 7)
`define GET_PTE_RSW(pte) (((pte) & `PTE_RSW_MASK) >> 8)
`define GET_PTE_PPN(pte) (((pte) & `PTE_PPN_MASK) >> 10)

`define SATP_MODE_MASK 32'h80000000
`define SATP_ASID_MASK 32'h7FC00000
`define SATP_PPN_MASK 32'h003FFFFF

`define SATP_MODE_SHIFT 31
`define SATP_ASID_SHIFT 22
`define SATP_PPN_SHIFT 0

`define SET_SATP_MODE(satp, mode) ((mode) << `SATP_MODE_SHIFT)
`define SET_SATP_ASID(satp, asid) ((asid) << `SATP_ASID_SHIFT)
`define SET_SATP_PPN(satp, ppn) ((ppn) << `SATP_PPN_SHIFT)

`define GET_SATP_MODE(satp) ((satp & `SATP_MODE_MASK) >> `SATP_MODE_SHIFT)
`define GET_SATP_ASID(satp) ((satp & `SATP_ASID_MASK) >> `SATP_ASID_SHIFT)
`define GET_SATP_PPN(satp) ((satp & `SATP_PPN_MASK) >> `SATP_PPN_SHIFT)

`endif

project/project_5/project_5.srcs/sources_1/imports/rtl/tag_ram.v
module tag_ram #(
  parameter TAG_RAM_ADDR_WIDTH = 6,
            TAG_WIDTH          = 20,
            PAYLOAD_WIDTH      = 32,
            WAYS               = 2
)(
  input  wire                    clk,
  input  wire                    resetn,
  input  wire [TAG_RAM_ADDR_WIDTH-1:0] idx,
  input  wire [TAG_WIDTH-1:0]    tag,
  input  wire [PAYLOAD_WIDTH-1:0] payload_i,
  input  wire                    we,
  input  wire                    valid_i,
  output reg                     hit_o,
  output reg [PAYLOAD_WIDTH-1:0] payload_o
);
  localparam LINES = 2**TAG_RAM_ADDR_WIDTH;
 (* ram_style = "block" *) reg [TAG_WIDTH-1:0]    tags   [WAYS-1:0][0:LINES-1];
 (* ram_style = "block" *) reg [PAYLOAD_WIDTH-1:0] payloads [WAYS-1:0][0:LINES-1];
 (* ram_style = "block" *) reg [WAYS-1:0]          v      [0:LINES-1];
 (* ram_style = "block" *) reg [0:0]               lru    [0:LINES-1];
  reg [0:0]               replace_way;
  integer i;

  // pick replace way
  always @(*) begin
    if (!v[idx][0])       replace_way = 0;
    else if (!v[idx][1])  replace_way = 1;
    else                  replace_way = lru[idx];
  end

  // read port
  always @(*) begin
    hit_o      = 0;
    payload_o  = 0;
    for (i=0; i<WAYS; i=i+1) begin
      if (v[idx][i] && tags[i][idx] == tag) begin
        hit_o     = 1;
        payload_o = payloads[i][idx];
      end
    end
  end

  // write port
  always @(posedge clk) begin
    if (!resetn) begin
      for (i=0; i<LINES; i=i+1) begin
        v[i]   <= 0;
        lru[i] <= 0;
      end
    end else if (we && valid_i) begin
      tags   [replace_way][idx] <= tag;
      payloads[replace_way][idx] <= payload_i;
      v      [idx][replace_way] <= 1;
      lru    [idx]             <= ~replace_way;
      $display("[TAGRAM] WWay%0d[%0d] T=%h D=%h",
               replace_way, idx, tag, payload_i);
    end
  end
endmodule

project/project_5/project_5.srcs/sources_1/imports/rtl/sv32.v
`timescale 1ns/1ps
`include "sv32.vh"

module sv32 #(
    parameter NUM_ENTRIES_ITLB = 64,
    parameter NUM_ENTRIES_DTLB = 64
) (
    input  wire        clk,
    input  wire        resetn,

    // CPU interface
    input  wire        cpu_valid,
    output reg         cpu_ready,
    input  wire [ 3:0] cpu_wstrb,
    input  wire [31:0] cpu_addr,
    input  wire [31:0] cpu_wdata,
    output reg  [31:0] cpu_rdata,

    // Memory interface
    output reg         mem_valid,
    input  wire        mem_ready,
    output reg  [ 3:0] mem_wstrb,
    output reg  [33:0] mem_addr,
    output reg  [31:0] mem_wdata,
    input  wire [31:0] mem_rdata,

    // Stats
    output wire [31:0] cache_miss_count,

    // Unused MMU signals for this cache example
    input  wire        is_instruction,
    input  wire        tlb_flush,
    output reg         stall,
    input  wire        write_back,
    input  wire [31:0] satp,
    input  wire [31:0] mstatus,
    input  wire [ 1:0] privilege_mode,
    output reg  [31:0] fault_address,
    output reg         page_fault
);

  // --------------------------------------------------
  // Simplified 2-way write-allocate cache logic
  // --------------------------------------------------

  // Index and tag from CPU address
  wire [5:0]  cache_idx = cpu_addr[17:12];
  wire [19:0] cache_tag = cpu_addr[31:12];
  wire        is_write  = |cpu_wstrb;

  // Cache datapath signals
  wire        hit;
  wire [31:0] hit_data;
  reg         cache_we;
  reg  [31:0] cache_wdata;

  // Miss counter
  reg [31:0] miss_count;
  always @(posedge clk) begin
    if (!resetn) miss_count <= 0;
    else if (cpu_valid && !hit) miss_count <= miss_count + 1;
  end
  assign cache_miss_count = miss_count;

  // Write state machine for write-back path
  localparam WR_IDLE  = 2'd0,
             WR_WAIT  = 2'd1;
  reg [1:0] wr_state;

  always @(posedge clk) begin
    if (!resetn) wr_state <= WR_IDLE;
    else begin
      case (wr_state)
        WR_IDLE: if (cpu_valid && is_write && !hit) wr_state <= WR_WAIT;
        WR_WAIT: if (mem_ready)                     wr_state <= WR_IDLE;
      endcase
    end
  end

  // Allocate state machine for read- or write-miss fill
  localparam AL_IDLE = 1'b0,
             AL_FILL = 1'b1;
  reg alloc_state;
  reg [5:0]   alloc_idx;
  reg [19:0]  alloc_tag;
  reg [31:0]  alloc_data;

  always @(posedge clk) begin
    if (!resetn) alloc_state <= AL_IDLE;
    else alloc_state <= (alloc_state == AL_FILL ? AL_IDLE :
             (cpu_valid && !hit && ((is_write && wr_state==WR_WAIT && mem_ready) ||
              (!is_write && mem_valid && mem_ready))) ? AL_FILL : AL_IDLE);

    // capture for AL_FILL
    if (alloc_state == AL_IDLE && cpu_valid && !hit && mem_ready) begin
      alloc_idx  <= cache_idx;
      alloc_tag  <= cache_tag;
      alloc_data <= is_write ? cpu_wdata : mem_rdata;
    end
  end

  // Drive memory interface
  always @(*) begin
    // defaults
    mem_valid = 0;
    mem_addr  = {2'b00, cpu_addr};
    mem_wstrb = cpu_wstrb;
    mem_wdata = cpu_wdata;
    // on read miss: issue read
    if (cpu_valid && !is_write && !hit) mem_valid = 1;
    // on write miss: issue write
    if (cpu_valid && is_write && !hit)  mem_valid = (wr_state==WR_WAIT);
  end

  // Cache write enable and data
  always @(*) begin
    cache_we    = 0;
    cache_wdata = 0;
    // write hit: write-through into cache
    if (cpu_valid && is_write && hit) begin
      cache_we    = 1;
      cache_wdata = cpu_wdata;
    end
    // miss allocate fill
    else if (alloc_state == AL_FILL) begin
      cache_we    = 1;
      cache_wdata = alloc_data;
    end
  end

  // CPU ready and read data registered
  always @(posedge clk) begin
    if (!resetn) begin
      cpu_ready <= 0;
      cpu_rdata <= 0;
    end else begin
      // hit: ready next cycle
      if (cpu_valid && hit) begin
        cpu_ready <= 1;
        cpu_rdata <= hit_data;
      end
      // miss fill: ready with alloc_data
      else if (alloc_state == AL_FILL) begin
        cpu_ready <= 1;
        cpu_rdata <= alloc_data;
      end else begin
        cpu_ready <= 0;
      end
    end
  end

  // Instantiate 2-way tag_ram
  tag_ram #(
    .TAG_RAM_ADDR_WIDTH(6),
    .TAG_WIDTH(20),
    .PAYLOAD_WIDTH(32),
    .WAYS(2)
  ) u_tag_ram (
    .clk      (clk),
    .resetn   (resetn),
    .idx      (alloc_state==AL_FILL ? alloc_idx : cache_idx),
    .tag      (alloc_state==AL_FILL ? alloc_tag : cache_tag),
    .payload_i(cache_wdata),
    .we       (cache_we),
    .valid_i  (cpu_valid),
    .hit_o    (hit),
    .payload_o(hit_data)
  );

endmodule

project/project_5/project_5.srcs/sim_1/imports/tb/cache_tb.v
`timescale 1ns/1ps

module cache_tb;

    reg clk;
    reg resetn;

    // 时钟生成
    initial begin
        clk = 0;
        forever #5 clk = ~clk;
    end

    // 复位生成
    initial begin
        resetn = 0;
        #20 resetn = 1;
    end

    // DUT接口
    reg         cpu_valid;
    reg [3:0]   cpu_wstrb;
    reg [31:0]  cpu_addr;
    reg [31:0]  cpu_wdata;
    wire [31:0] cpu_rdata;
    wire        cpu_ready;

    wire        mem_valid;
    reg         mem_ready;
    wire [3:0]  mem_wstrb;
    wire [33:0] mem_addr;
    wire [31:0] mem_wdata;
    reg  [31:0] mem_rdata;

    wire [31:0] cache_miss_count;
    wire        is_instruction = 0;
    wire        tlb_flush = 0;
    wire        stall;
    wire        write_back = 0;
    wire [31:0] satp = 0;
    wire [31:0] mstatus = 0;
    wire [1:0]  privilege_mode = 3;
    wire [31:0] fault_address;
    wire        page_fault;

    // 内存模型
    reg [31:0] memory [0:1023];  // 1KB内存空间
    integer i; // 声明i

    // 实例化DUT
    sv32 u_dut (
        .clk(clk),
        .resetn(resetn),
        .cpu_valid(cpu_valid),
        .cpu_ready(cpu_ready),
        .cpu_wstrb(cpu_wstrb),
        .cpu_addr(cpu_addr),
        .cpu_wdata(cpu_wdata),
        .cpu_rdata(cpu_rdata),
        .mem_valid(mem_valid),
        .mem_ready(mem_ready),
        .mem_wstrb(mem_wstrb),
        .mem_addr(mem_addr),
        .mem_wdata(mem_wdata),
        .mem_rdata(mem_rdata),
        .cache_miss_count(cache_miss_count),
        .is_instruction(is_instruction),
        .tlb_flush(tlb_flush),
        .stall(stall),
        .write_back(write_back),
        .satp(satp),
        .mstatus(mstatus),
        .privilege_mode(privilege_mode),
        .fault_address(fault_address),
        .page_fault(page_fault)
    );

    // 行为级内存模型
    always @(posedge clk) begin
        if (mem_valid) begin
            // 写操作
            if (|mem_wstrb) begin
                memory[mem_addr[31:2]] <= mem_wdata;  // 字地址对齐
                $display("[MEM] Write Addr=%h Data=%h", 
                        mem_addr, mem_wdata);
            end 
            // 读操作
            else begin
                mem_rdata <= memory[mem_addr[31:2]];
                $display("[MEM] Read Addr=%h Data=%h", 
                        mem_addr, mem_rdata);
            end
            mem_ready <= 1'b1;
        end else begin
            mem_ready <= 1'b0;
        end
    end

    // 新增统计相关变量
    integer total_misses = 0;
    integer current_test_misses = 0;
    integer test_case_num = 1;
    integer expected_misses[1:3];  // 存储各测试用例预期未命中数

    // 主测试流程
    initial begin
        // 初始化
        cpu_valid = 0;
        cpu_wstrb = 0;
        cpu_addr = 0;
        cpu_wdata = 0;
        mem_ready = 0;
        mem_rdata = 0;
        
        // 初始化内存
        for (i = 0; i < 1024; i = i + 1) begin
            memory[i] = 32'h0;
        end

        // 等待复位完成
        wait(resetn);
        #30;

        // 设置预期未命中数
        expected_misses[1] = 2;  // Test1: 写未命中+读未命中
        expected_misses[2] = 3;  // Test2: 写Way0+写Way1+替换写
        expected_misses[3] = 1;  // Test3: 写未命中

        // ============ 测试1：基本写后读 ============
        $display("\n=== 测试1：基本写后读验证 ===");
        begin_test_case();
        test_write(32'h1000, 32'h11223344);
        test_read(32'h1000, 32'h11223344);
        end_test_case(1);

        // ============ 测试2：缓存替换 ============
        $display("\n=== 测试2：缓存替换验证 ===");
        begin_test_case();
        test_write(32'h2000, 32'hAABBCCDD); // Way0[0]
        test_write(32'h3000, 32'hDDCCBBAA); // Way1[0]
        test_write(32'h4000, 32'h12345678); // 应替换LRU路
        test_read(32'h4000, 32'h12345678);
        end_test_case(2);

        // ============ 测试3：写未命中 ============
        $display("\n=== 测试3：写未命中验证 ===");
        begin_test_case();
        test_write(32'h5000, 32'h55AA55AA);
        test_read(32'h5000, 32'h55AA55AA);
        end_test_case(3);

        // 显示最终统计
        $display("\n============ 缓存性能统计 ============");
        $display("| 测试用例 | 预期未命中 | 实际未命中 | 状态 |");
        $display("|----------|------------|------------|------|");
        $display("|   Test1  |     %2d     |     %2d     | %s |",
                expected_misses[1], 
                get_miss_count(1),
                (get_miss_count(1)==expected_misses[1]) ? "通过" : "失败");
        $display("|   Test2  |     %2d     |     %2d     | %s |",
                expected_misses[2], 
                get_miss_count(2),
                (get_miss_count(2)==expected_misses[2]) ? "通过" : "失败");
        $display("|   Test3  |     %2d     |     %2d     | %s |",
                expected_misses[3], 
                get_miss_count(3),
                (get_miss_count(3)==expected_misses[3]) ? "通过" : "失败");
        $display("----------------------------------------");
        $display("|  总计    |     %2d     |     %2d     |      |",
                expected_misses[1]+expected_misses[2]+expected_misses[3],
                total_misses);
        $display("========================================");

        #50 $finish;
    end

    // ================= 测试任务 =================
    task test_write;
        input [31:0] addr;
        input [31:0] data;
    begin
        cpu_addr = addr;
        cpu_wdata = data;
        cpu_wstrb = 4'hF;
        cpu_valid = 1;
        
        wait(cpu_ready);
        @(posedge clk);
        cpu_valid = 0;
        cpu_wstrb = 0;
        
        $display("[TEST] 写入地址：0x%h，数据：0x%h", addr, data);
        #20;
    end
    endtask

    task test_read;
        input [31:0] addr;
        input [31:0] expected;
    begin
        cpu_addr = addr;
        cpu_wstrb = 0;
        cpu_valid = 1;
        
        wait(cpu_ready);
        @(posedge clk);
        cpu_valid = 0;
        
        if (cpu_rdata === expected) begin
            $display("[TEST] 读取地址：0x%h，数据正确：0x%h", addr, cpu_rdata);
        end else begin
            $error("[ERROR] 地址0x%h 数据错误！期望：0x%h，实际：0x%h",
                  addr, expected, cpu_rdata);
        end
        #20;
    end
    endtask

    // ================= 新增统计任务 =================
    task begin_test_case;
    begin
        current_test_misses = u_dut.cache_miss_count;
        $display("[STAT] 开始测试用例 %0d，当前未命中数：%0d", 
                test_case_num, current_test_misses);
    end
    endtask

    task end_test_case;
        input integer tc_num;
        integer actual_misses;
    begin
        actual_misses = u_dut.cache_miss_count - current_test_misses;
        total_misses = actual_misses + total_misses;
        $display("[STAT] 测试用例 %0d 结果：", tc_num);
        $display("   预期未命中：%0d", expected_misses[tc_num]);
        $display("   实际未命中：%0d", actual_misses);
        $display("   内存访问次数：%0d", actual_misses);
        test_case_num =  1 + test_case_num;
        #20;
    end
    endtask

    function integer get_miss_count;
        input integer tc;
    begin
        case(tc)
            1: get_miss_count = expected_misses[1];
            2: get_miss_count = expected_misses[2];
            3: get_miss_count = expected_misses[3];
            default: get_miss_count = 0;
        endcase
    end
    endfunction

    // ================= 波形记录 =================
    initial begin
        $dumpfile("wave.vcd");
        $dumpvars(0, cache_tb);
        // 记录DUT内部信号
        $dumpvars(1, u_dut.u_tag_ram.tags);
        $dumpvars(1, u_dut.u_tag_ram.payloads);
        $dumpvars(1, u_dut.u_tag_ram.v);
        $dumpvars(1, u_dut.u_tag_ram.lru);
    end

endmodule

project/project_5/project_5.sim/sim_1/behav/xsim/wave.vcd
$date
   Sat May 10 11:20:42 2025
$end

$version
  2024.2.0
  $dumpfile ("wave.vcd") 
$end

$timescale
  1ps
$end

$scope module cache_tb $end
$var reg 1 ! clk $end
$var reg 1 " resetn $end
$var reg 1 # cpu_valid $end
$var reg 4 $ cpu_wstrb [3:0] $end
$var reg 32 % cpu_addr [31:0] $end
$var reg 32 & cpu_wdata [31:0] $end
$var wire 32 ' cpu_rdata [31:0] $end
$var wire 1 ( cpu_ready $end
$var wire 1 ) mem_valid $end
$var reg 1 * mem_ready $end
$var wire 4 + mem_wstrb [3:0] $end
$var wire 34 , mem_addr [33:0] $end
$var wire 32 - mem_wdata [31:0] $end
$var reg 32 . mem_rdata [31:0] $end
$var wire 32 / cache_miss_count [31:0] $end
$var wire 1 0 is_instruction $end
$var wire 1 1 tlb_flush $end
$var wire 1 2 stall $end
$var wire 1 3 write_back $end
$var wire 32 4 satp [31:0] $end
$var wire 32 5 mstatus [31:0] $end
$var wire 2 6 privilege_mode [1:0] $end
$var wire 32 7 fault_address [31:0] $end
$var wire 1 8 page_fault $end
$var integer 32 9 i [31:0] $end
$var integer 32 : total_misses [31:0] $end
$var integer 32 ; current_test_misses [31:0] $end
$var integer 32 < test_case_num [31:0] $end
$scope module u_dut $end
$var wire 1 = clk $end
$var wire 1 > resetn $end
$var wire 1 ? cpu_valid $end
$var reg 1 @ cpu_ready $end
$var wire 4 A cpu_wstrb [3:0] $end
$var wire 32 B cpu_addr [31:0] $end
$var wire 32 C cpu_wdata [31:0] $end
$var reg 32 D cpu_rdata [31:0] $end
$var reg 1 E mem_valid $end
$var wire 1 F mem_ready $end
$var reg 4 G mem_wstrb [3:0] $end
$var reg 34 H mem_addr [33:0] $end
$var reg 32 I mem_wdata [31:0] $end
$var wire 32 J mem_rdata [31:0] $end
$var wire 32 / cache_miss_count [31:0] $end
$var wire 1 0 is_instruction $end
$var wire 1 1 tlb_flush $end
$var reg 1 K stall $end
$var wire 1 3 write_back $end
$var wire 32 4 satp [31:0] $end
$var wire 32 5 mstatus [31:0] $end
$var wire 2 6 privilege_mode [1:0] $end
$var reg 32 L fault_address [31:0] $end
$var reg 1 M page_fault $end
$var wire 6 N cache_idx [5:0] $end
$var wire 20 O cache_tag [19:0] $end
$var wire 1 P is_write $end
$var wire 1 Q hit $end
$var wire 32 R hit_data [31:0] $end
$var reg 1 S cache_we $end
$var reg 32 T cache_wdata [31:0] $end
$var reg 32 U miss_count [31:0] $end
$var reg 2 V wr_state [1:0] $end
$var reg 1 W alloc_state $end
$var reg 6 X alloc_idx [5:0] $end
$var reg 20 Y alloc_tag [19:0] $end
$var reg 32 Z alloc_data [31:0] $end
$scope module u_tag_ram $end
$var wire 1 = clk $end
$var wire 1 > resetn $end
$var wire 6 [ idx [5:0] $end
$var wire 20 \ tag [19:0] $end
$var wire 32 ] payload_i [31:0] $end
$var wire 1 ^ we $end
$var wire 1 ? valid_i $end
$var reg 1 _ hit_o $end
$var reg 32 ` payload_o [31:0] $end
$var reg 1 a replace_way [0:0] $end
$var integer 32 b i [31:0] $end
$upscope $end
$upscope $end
$scope task test_write $end
$var reg 32 c addr [31:0] $end
$var reg 32 d data [31:0] $end
$upscope $end
$scope task test_read $end
$var reg 32 e addr [31:0] $end
$var reg 32 f expected [31:0] $end
$upscope $end
$scope task begin_test_case $end
$upscope $end
$scope task end_test_case $end
$var integer 32 g tc_num [31:0] $end
$var integer 32 h actual_misses [31:0] $end
$upscope $end
$scope function get_miss_count $end
$var integer 32 i get_miss_count [31:0] $end
$var integer 32 j tc [31:0] $end
$upscope $end
$upscope $end
$enddefinitions $end

#0
$dumpvars
0!
0"
0#
b0 $
b0 %
b0 &
bx '
x(
0)
0*
b0 +
b0 ,
b0 -
b0 .
bx /
00
01
x2
03
b0 4
b0 5
b11 6
bx 7
x8
b10000000000 9
b0 :
b0 ;
b1 <
0=
0>
0?
x@
b0 A
b0 B
b0 C
bx D
0E
0F
b0 G
b0 H
b0 I
b0 J
xK
bx L
xM
b0 N
b0 O
0P
xQ
bx R
0S
b0 T
bx U
bx V
xW
bx X
bx Y
bx Z
bx [
bx \
b0 ]
0^
x_
bx `
xa
bx b
bx c
bx d
bx e
bx f
bx g
bx h
bx i
bx j
$end

#5000
1!
b0 '
0(
b0 /
1=
0@
b0 D
0Q
b0 R
b0 U
b0 V
0W
b0 [
b0 \
0_
b0 `
0a
b10 b

#10000
0!
0=

#15000
1!
1=
b1000000 b

#20000
0!
1"
0=
1>

#25000
1!
1=

#30000
0!
0=

#35000
1!
1=

#40000
0!
0=

#45000
1!
1=

#50000
0!
1#
b1111 $
b1000000000000 %
b10001001000100011001101000100 &
b1111 +
b1000000000000 ,
b10001001000100011001101000100 -
0=
1?
b1111 A
b1000000000000 B
b10001001000100011001101000100 C
b1111 G
b1000000000000 H
b10001001000100011001101000100 I
b1 N
b1 O
1P
b1 [
b1 \
b10 b
b1000000000000 c
b10001001000100011001101000100 d

#55000
1!
1)
b1 /
1=
1E
b1 U
b1 V

#60000
0!
0=

#65000
1!
1*
b10 /
1=
1F
b10 U

#70000
0!
0=

#75000
1!
0)
b11 /
1=
0E
1S
b10001001000100011001101000100 T
b11 U
b0 V
1W
b1 X
b1 Y
b10001001000100011001101000100 Z
b10001001000100011001101000100 ]
1^

#80000
0!
0=

#85000
1!
b10001001000100011001101000100 '
1(
0)
0*
b100 /
1=
1@
b10001001000100011001101000100 D
0E
0F
1Q
b10001001000100011001101000100 R
1S
b10001001000100011001101000100 T
b100 U
b1 V
0W
b10001001000100011001101000100 ]
1^
1_
b10001001000100011001101000100 `
1a
b10 b

#90000
0!
0=

#95000
1!
0#
b0 $
0(
b0 +
1=
0?
0@
b0 A
b0 G
0P
0S
b0 T
b0 ]
0^

#100000
0!
0=

#105000
1!
1=

#110000
0!
0=

#115000
1!
1#
1(
1=
1?
1@
b1000000000000 e
b10001001000100011001101000100 f

#120000
0!
0=

#125000
1!
0#
0(
1=
0?
0@

#130000
0!
0=

#135000
1!
1=

#140000
0!
0=

#145000
1!
b100 :
b10 <
1=
b1 g
b100 h

#150000
0!
0=

#155000
1!
1=

#160000
0!
0=

#165000
1!
1#
b1111 $
b10000000000000 %
b10101010101110111100110011011101 &
1(
0)
b1111 +
b10000000000000 ,
b10101010101110111100110011011101 -
b100 ;
1=
1?
1@
b1111 A
b10000000000000 B
b10101010101110111100110011011101 C
0E
b1111 G
b10000000000000 H
b10101010101110111100110011011101 I
b10 N
b10 O
1P
1Q
b10101010101110111100110011011101 R
1S
b10101010101110111100110011011101 T
b10 [
b10 \
b10101010101110111100110011011101 ]
1^
1_
b10101010101110111100110011011101 `
0a
b10 b
b10000000000000 c
b10101010101110111100110011011101 d

#170000
0!
0=

#175000
1!
0#
b0 $
0(
b0 +
1=
0?
0@
b0 A
b0 G
0P
0S
b0 T
b0 ]
0^

#180000
0!
0=

#185000
1!
1=

#190000
0!
0=

#195000
1!
1#
b1111 $
b11000000000000 %
b11011101110011001011101110101010 &
b10101010101110111100110011011101 '
1(
0)
b1111 +
b11000000000000 ,
b11011101110011001011101110101010 -
1=
1?
1@
b1111 A
b11000000000000 B
b11011101110011001011101110101010 C
b10101010101110111100110011011101 D
0E
b1111 G
b11000000000000 H
b11011101110011001011101110101010 I
b11 N
b11 O
1P
1Q
b11011101110011001011101110101010 R
1S
b11011101110011001011101110101010 T
b11 [
b11 \
b11011101110011001011101110101010 ]
1^
1_
b11011101110011001011101110101010 `
1a
b10 b
b11000000000000 c
b11011101110011001011101110101010 d

#200000
0!
0=

#205000
1!
0#
b0 $
0(
b0 +
1=
0?
0@
b0 A
b0 G
0P
0S
b0 T
b0 ]
0^

#210000
0!
0=

#215000
1!
1=

#220000
0!
0=

#225000
1!
1#
b1111 $
b100000000000000 %
b10010001101000101011001111000 &
b11011101110011001011101110101010 '
1(
0)
b1111 +
b100000000000000 ,
b10010001101000101011001111000 -
1=
1?
1@
b1111 A
b100000000000000 B
b10010001101000101011001111000 C
b11011101110011001011101110101010 D
0E
b1111 G
b100000000000000 H
b10010001101000101011001111000 I
b100 N
b100 O
1P
1Q
b10010001101000101011001111000 R
1S
b10010001101000101011001111000 T
b100 [
b100 \
b10010001101000101011001111000 ]
1^
1_
b10010001101000101011001111000 `
0a
b10 b
b100000000000000 c
b10010001101000101011001111000 d

#230000
0!
0=

#235000
1!
0#
b0 $
0(
b0 +
1=
0?
0@
b0 A
b0 G
0P
0S
b0 T
b0 ]
0^

#240000
0!
0=

#245000
1!
1=

#250000
0!
0=

#255000
1!
1#
b10010001101000101011001111000 '
1(
1=
1?
1@
b10010001101000101011001111000 D
b100000000000000 e
b10010001101000101011001111000 f

#260000
0!
0=

#265000
1!
0#
0(
1=
0?
0@

#270000
0!
0=

#275000
1!
1=

#280000
0!
0=

#285000
1!
b11 <
1=
b10 g
b0 h

#290000
0!
0=

#295000
1!
1=

#300000
0!
0=

#305000
1!
1#
b1111 $
b101000000000000 %
b1010101101010100101010110101010 &
1(
0)
b1111 +
b101000000000000 ,
b1010101101010100101010110101010 -
1=
1?
1@
b1111 A
b101000000000000 B
b1010101101010100101010110101010 C
0E
b1111 G
b101000000000000 H
b1010101101010100101010110101010 I
b101 N
b101 O
1P
1Q
b1010101101010100101010110101010 R
1S
b1010101101010100101010110101010 T
b101 [
b101 \
b1010101101010100101010110101010 ]
1^
1_
b1010101101010100101010110101010 `
1a
b10 b
b101000000000000 c
b1010101101010100101010110101010 d

#310000
0!
0=

#315000
1!
0#
b0 $
0(
b0 +
1=
0?
0@
b0 A
b0 G
0P
0S
b0 T
b0 ]
0^

#320000
0!
0=

#325000
1!
1=

#330000
0!
0=

#335000
1!
1#
b1010101101010100101010110101010 '
1(
1=
1?
1@
b1010101101010100101010110101010 D
b101000000000000 e
b1010101101010100101010110101010 f

#340000
0!
0=

#345000
1!
0#
0(
1=
0?
0@

#350000
0!
0=

#355000
1!
1=

#360000
0!
0=

#365000
1!
b100 <
1=
b11 g

#370000
0!
0=

#375000
1!
1=

#380000
0!
0=

#385000
1!
1=
b1 i
b11 j

